logpyle/__init__.py
logpyle/py.typed
logpyle/runalyzer.py
logpyle/runalyzer_gather.py
logpyle/upgrade_db.py
logpyle/version.py
logpyle/HTMLalyzer/__init__.py
logpyle/HTMLalyzer/file_hashes.txt
logpyle/HTMLalyzer/htmlalyzer.html
logpyle/HTMLalyzer/main.css
logpyle/HTMLalyzer/main.js
logpyle/HTMLalyzer/main.py
logpyle/HTMLalyzer/pymbolic-2022.2-py3-none-any.whl
logpyle/HTMLalyzer/templates/index.html
logpyle/HTMLalyzer/templates/newFile.html
logpyle-2025.1.data/scripts/htmlalyzer
logpyle-2025.1.data/scripts/logtool
logpyle-2025.1.data/scripts/runalyzer
logpyle-2025.1.data/scripts/runalyzer-gather
logpyle-2025.1.data/scripts/upgrade-db
logpyle-2025.1.dist-info/licenses/LICENSE
logpyle-2025.1.dist-info/METADATA
logpyle-2025.1.dist-info/WHEEL
logpyle-2025.1.dist-info/top_level.txt
logpyle-2025.1.dist-info/RECORD
